ai_blog_app/__init__.py
ai_blog_app/config.py
ai_blog_app/llm_config.json
ai_blog_app/agents/__init__.py
ai_blog_app/agents/critic.py
ai_blog_app/agents/reviewers.py
ai_blog_app/agents/writer.py
ai_blog_app/utils/__init__.py
ai_blog_app/utils/helpers.py
ai_blog_app-1.0.6.dist-info/licenses/LICENSE
ai_blog_app-1.0.6.dist-info/METADATA
ai_blog_app-1.0.6.dist-info/WHEEL
ai_blog_app-1.0.6.dist-info/top_level.txt
ai_blog_app-1.0.6.dist-info/RECORD
