Metadata-Version: 2.4
Name: ai-blog-app
Version: 1.0.6
Summary: A modular AI application for creating high-engagement blog posts. This framework supports multiple LLMs, optional PDF context, and customizable article length.
Author-email: Edilma Riano <EdilmaDev@Gmail.com>
License: MIT License
Project-URL: Homepage, https://github.com/edilma/AI_Blog_App
Project-URL: Documentation, https://github.com/edilma/AI_Blog_App/blob/main/README.md
Project-URL: BugTracker, https://github.com/edilma/AI_Blog_App/issues
Keywords: ai,blog,autogen,llm,agent,content-generation
Classifier: Programming Language :: Python :: 3
Classifier: Programming Language :: Python :: 3.10
Classifier: Programming Language :: Python :: 3.11
Classifier: Programming Language :: Python :: 3.12
Classifier: License :: OSI Approved :: MIT License
Classifier: Operating System :: OS Independent
Classifier: Topic :: Scientific/Engineering :: Artificial Intelligence
Classifier: Topic :: Software Development :: Libraries
Classifier: Topic :: Text Processing :: General
Classifier: Topic :: Internet :: WWW/HTTP :: Dynamic Content
Classifier: Topic :: Utilities
Requires-Python: >=3.10
License-File: LICENSE
Requires-Dist: autogen-agentchat>=0.7.1
Requires-Dist: autogen-ext[all]>=0.7.1
Requires-Dist: openai>=1.98.0
Requires-Dist: tiktoken>=0.11.0
Provides-Extra: fastapi
Requires-Dist: fastapi; extra == "fastapi"
Requires-Dist: uvicorn[standard]; extra == "fastapi"
Dynamic: license-file
